random_scraper/__init__.py
random_scraper/random_scraper.py
random_scraper/package_data/.DS_Store
random_scraper/package_data/user-agents.txt
random_scraper-0.0.3.data/scripts/random_scrape
random_scraper-0.0.3.dist-info/LICENSE
random_scraper-0.0.3.dist-info/METADATA
random_scraper-0.0.3.dist-info/WHEEL
random_scraper-0.0.3.dist-info/top_level.txt
random_scraper-0.0.3.dist-info/RECORD
