Metadata-Version: 2.1
Name: random-scraper
Version: 0.0.3
Summary: Tools for Web-Scraping
Home-page: https://github.com/random-scraper/random_scraper/
Author: Malek Ben Sliman
Author-email: mab2343@columbia.edu
License: UNKNOWN
Platform: UNKNOWN
Classifier: Programming Language :: Python :: 3.7
Classifier: License :: OSI Approved :: GNU General Public License v3 (GPLv3)
Requires-Dist: requests
Requires-Dist: lxml
